prizm/__init__.py
prizm/console.py
prizm/util/__init__.py
prizm/util/benchmark.py
prizm/util/color.py
prizm/util/debug.py
prizm/util/fast_date_range.py
prizm/util/file.py
prizm/util/loader.py
pyprizm-0.1.1.dist-info/METADATA
pyprizm-0.1.1.dist-info/WHEEL
pyprizm-0.1.1.dist-info/top_level.txt
pyprizm-0.1.1.dist-info/RECORD
